odoo/addons/purchase_work_acceptance_tier_validation/README.rst
odoo/addons/purchase_work_acceptance_tier_validation/__init__.py
odoo/addons/purchase_work_acceptance_tier_validation/__manifest__.py
odoo/addons/purchase_work_acceptance_tier_validation/i18n/purchase_work_acceptance_tier_validation.pot
odoo/addons/purchase_work_acceptance_tier_validation/models/__init__.py
odoo/addons/purchase_work_acceptance_tier_validation/models/tier_definition.py
odoo/addons/purchase_work_acceptance_tier_validation/models/work_acceptance.py
odoo/addons/purchase_work_acceptance_tier_validation/readme/CONFIGURE.rst
odoo/addons/purchase_work_acceptance_tier_validation/readme/CONTRIBUTORS.rst
odoo/addons/purchase_work_acceptance_tier_validation/readme/DESCRIPTION.rst
odoo/addons/purchase_work_acceptance_tier_validation/readme/INSTALL.rst
odoo/addons/purchase_work_acceptance_tier_validation/readme/USAGE.rst
odoo/addons/purchase_work_acceptance_tier_validation/static/description/icon.png
odoo/addons/purchase_work_acceptance_tier_validation/static/description/index.html
odoo/addons/purchase_work_acceptance_tier_validation/tests/__init__.py
odoo/addons/purchase_work_acceptance_tier_validation/tests/test_purchast_work_acceptance_tier_validation.py
odoo/addons/purchase_work_acceptance_tier_validation/views/work_acceptance_view.xml
odoo_addon_purchase_work_acceptance_tier_validation-15.0.1.0.0.4.dist-info/METADATA
odoo_addon_purchase_work_acceptance_tier_validation-15.0.1.0.0.4.dist-info/WHEEL
odoo_addon_purchase_work_acceptance_tier_validation-15.0.1.0.0.4.dist-info/top_level.txt
odoo_addon_purchase_work_acceptance_tier_validation-15.0.1.0.0.4.dist-info/RECORD
