Metadata-Version: 2.1
Name: odoo-addon-purchase-work-acceptance-tier-validation
Version: 15.0.1.0.0.4
Summary: Extends the functionality of Work Acceptance to support a tier validation process.
Home-page: https://github.com/OCA/purchase-workflow
Author: Ecosoft, Odoo Community Association (OCA)
Author-email: support@odoo-community.org
License: AGPL-3
Platform: UNKNOWN
Classifier: Programming Language :: Python
Classifier: Framework :: Odoo
Classifier: Framework :: Odoo :: 15.0
Classifier: License :: OSI Approved :: GNU Affero General Public License v3
Classifier: Development Status :: 3 - Alpha
Requires-Python: >=3.8
Requires-Dist: odoo-addon-base-tier-validation <15.1dev,>=15.0dev
Requires-Dist: odoo-addon-purchase-work-acceptance <15.1dev,>=15.0dev
Requires-Dist: odoo <15.1dev,>=15.0a
